{
  "중1": {
    "내신": {
      "능률": ["1과 능률 중1","2과 능률 중1","3과 능률 중1"],
      "천재": ["1과 천재 중1","2과 천재 중1","3과 천재 중1"],
      "미래엔": ["1과 미래엔 중1","2과 미래엔 중1","3과 미래엔 중1"]
    },
    "성취도평가": {
      "2024": ["3월","6월","9월"],
      "2023": ["3월","6월","9월"],
      "2021": ["3월","6월","9월"]
    }
  },
  "중2": {
    "내신": {
      "능률": ["1과 중2","2과 중2","3과 중2"],
      "천재": ["1과 중2","2과 중2","3과 중2"],
      "미래엔": ["1과 중2","2과 중2","3과 중2"]
    },
    "성취도평가": {
      "2024": ["3월","6월","9월"],
      "2023": ["3월","6월","9월"],
      "2021": ["3월","6월","9월"]
    }
  },
  "중3": {
    "내신": {
      "능률": ["01 강조의 DO","02 가정법","03 관계대명사"],
      "천재": ["01 관계부사","02 not only but also 구문","03 분사구문"],
      "미래엔": ["01 지각동사와 사역동사","02 과거완료","03 도치구문"]
    },
    "성취도평가": {
      "2024": ["3월","6월","9월"],
      "2023": ["3월","6월","9월"],
      "2021": ["3월","6월","9월"]
    }
  },
  "고1": {
    "내신": {
      "능률": ["1과 고1","2과 고1","3과 고1"],
      "천재": ["1과 고1","2과 고1","3과 고1"],
      "미래엔": ["1과 고1","2과 고1","3과 고1"]
    },
    "수능": {
      "2024": ["3월","6월","9월"],
      "2023": ["3월","6월","9월"],
      "2021": ["3월","6월","9월"]
    }
  },
  "고2": {
    "내신": {
      "능률": ["1과 고2","2과 고2","3과 고2"],
      "천재": ["1과 고2","2과 고2","3과 고2"],
      "미래엔": ["1과 고2","2과 고2","3과 고2"]
    },
    "수능": {
      "2024": ["3월","6월","9월"],
      "2023": ["3월","6월","9월"],
      "2021": ["3월","6월","9월"]
    }
  },
  "고3": {
    "내신": {
      "능률": ["1과 고3","2과 고3","3과 고3"],
      "천재": ["1과 고3","2과 고3","3과 고3"],
      "미래엔": ["1과 고3","2과 고3","3과 고3"]
    },
    "수능": {
      "2024": ["3월","6월","9월"],
      "2023": ["3월","6월","9월"],
      "2021": ["3월","6월","9월"]
    }
  }
}
